quickle.cpython-38-x86_64-linux-gnu.so
quickle-0.4.0.dist-info/top_level.txt
quickle-0.4.0.dist-info/RECORD
quickle-0.4.0.dist-info/METADATA
quickle-0.4.0.dist-info/LICENSE
quickle-0.4.0.dist-info/WHEEL
tests/test_struct.py
tests/__init__.py
tests/test_quickle.py
