Metadata-Version: 2.1
Name: quickle
Version: 0.4.0
Summary: A quicker pickle
Home-page: https://jcristharif.com/quickle/
Maintainer: Jim Crist-Harif
Maintainer-email: jcristharif@gmail.com
License: BSD
Project-URL: Documentation, https://jcristharif.com/quickle/
Project-URL: Source, https://github.com/jcrist/quickle/
Project-URL: Issue Tracker, https://github.com/jcrist/quickle/issues
Platform: UNKNOWN
Classifier: License :: OSI Approved :: BSD License
Classifier: Programming Language :: Python :: 3.8
Classifier: Programming Language :: Python :: 3.9
Requires-Python: >=3.8
